CHANGELOG.txt
LICENSE.txt
MANIFEST.in
README.txt
setup.py
basic_calculator/__init__.py
diffstep.egg-info/PKG-INFO
diffstep.egg-info/SOURCES.txt
diffstep.egg-info/dependency_links.txt
diffstep.egg-info/top_level.txt