Metadata-Version: 2.1
Name: diffstep
Version: 0.0.1
Summary: This is a library for Algorithmic Differentiation.
Home-page: 
Author: Ayo
Author-email: akoitilo@gmail.com
Keywords: differentiation
License-File: LICENSE.txt
